idos_scraper/__init__.py
idos_scraper/log.py
idos_scraper/examples/async_search_and_page_connection.py
idos_scraper/examples/search_and_page_connection.py
idos_scraper/examples/ui_search_station.py
idos_scraper/scrapers/__init__.py
idos_scraper/scrapers/async_page_connections.py
idos_scraper/scrapers/async_search_connections.py
idos_scraper/scrapers/async_search_station.py
idos_scraper/scrapers/page_connections.py
idos_scraper/scrapers/search_connections.py
idos_scraper/scrapers/search_station.py
idos_scraper-0.2.4.dist-info/METADATA
idos_scraper-0.2.4.dist-info/WHEEL
idos_scraper-0.2.4.dist-info/licenses/LICENSE
idos_scraper-0.2.4.dist-info/RECORD
