Metadata-Version: 2.3
Name: idos-scraper
Version: 0.2.4
Summary: Scrapes Czech public transport data from IDOS
Project-URL: Homepage, https://github.com/Tomdein/idos-scraper
Project-URL: Repository, https://github.com/Tomdein/idos-scraper
Project-URL: Documentation, https://github.com/Tomdein/idos-scraper
Project-URL: Bug Tracker, https://github.com/Tomdein/idos-scraper/issues
Author-email: Tomas Deingruber <Deingruber.Tomas+idos-scraper@gmail.com>
License-File: LICENSE
Classifier: License :: OSI Approved :: MIT License
Classifier: Operating System :: OS Independent
Classifier: Programming Language :: Python :: 3
Requires-Python: >=3.7
Requires-Dist: aiohttp>=3.8
Requires-Dist: beautifulsoup4>=4.11
Requires-Dist: pysimplegui>=4.30
